llm_factory/__init__.py
llm_factory/llm_base.py
llm_factory/llm_factory.py
llm_factory/llm_openai_chat.py
microlearn_llm_factory-0.0.10.dist-info/METADATA
microlearn_llm_factory-0.0.10.dist-info/WHEEL
microlearn_llm_factory-0.0.10.dist-info/top_level.txt
microlearn_llm_factory-0.0.10.dist-info/RECORD
